athvavavav/__init__.py
athvavavav/hello.py
athvavavav-0.0.1.dist-info/METADATA
athvavavav-0.0.1.dist-info/WHEEL
athvavavav-0.0.1.dist-info/top_level.txt
athvavavav-0.0.1.dist-info/RECORD
